odoo/addons/geoengine_partner/README.rst
odoo/addons/geoengine_partner/__init__.py
odoo/addons/geoengine_partner/__manifest__.py
odoo/addons/geoengine_partner/i18n/geoengine_partner.pot
odoo/addons/geoengine_partner/models/__init__.py
odoo/addons/geoengine_partner/models/partner.py
odoo/addons/geoengine_partner/static/description/icon.png
odoo/addons/geoengine_partner/views/partner.xml
odoo11_addon_geoengine_partner-11.0.1.0.0.99.dev3.dist-info/METADATA
odoo11_addon_geoengine_partner-11.0.1.0.0.99.dev3.dist-info/WHEEL
odoo11_addon_geoengine_partner-11.0.1.0.0.99.dev3.dist-info/top_level.txt
odoo11_addon_geoengine_partner-11.0.1.0.0.99.dev3.dist-info/RECORD
